LICENSE
telepay/__init__.py
telepay/v1/__init__.py
telepay/v1/_async/__init__.py
telepay/v1/_async/client.py
telepay/v1/_sync/__init__.py
telepay/v1/_sync/client.py
telepay/v1/auth.py
telepay/v1/errors.py
telepay/v1/http_clients.py
telepay/v1/models/__init__.py
telepay/v1/models/account.py
telepay/v1/models/assets.py
telepay/v1/models/invoice.py
telepay/v1/models/wallets.py
telepay/v1/models/webhooks.py
telepay/v1/utils.py
telepay/v1/webhooks.py
telepay-1.1.0.dist-info/METADATA
telepay-1.1.0.dist-info/WHEEL
telepay-1.1.0.dist-info/LICENSE
telepay-1.1.0.dist-info/RECORD
