Metadata-Version: 2.1
Name: telepay
Version: 1.1.0
Summary: Python SDK for the TelePay API
Home-page: https://github.com/TelePay-cash/telepay-python
License: MIT
Keywords: payments,gateway,cryptocurrencies,API
Author: Carlos Lugones
Requires-Python: >=3.10,<4.0
Classifier: Development Status :: 4 - Beta
Classifier: Environment :: Console
Classifier: Intended Audience :: Developers
Classifier: License :: OSI Approved :: MIT License
Classifier: Natural Language :: English
Classifier: Operating System :: OS Independent
Classifier: Programming Language :: Python
Classifier: Programming Language :: Python :: 3
Classifier: Programming Language :: Python :: 3.10
Classifier: Programming Language :: Python :: 3.11
Classifier: Topic :: Software Development :: Libraries :: Python Modules
Requires-Dist: colorama (>=0.4.4,<0.5.0)
Requires-Dist: fastapi (>=0.75.1,<0.76.0)
Requires-Dist: httpx (>=0.23.0,<0.24.0)
Requires-Dist: python-dotenv (>=0.20.0,<0.21.0)
Requires-Dist: uvicorn (>=0.17.6,<0.18.0)
Project-URL: Bug Tracker, https://github.com/TelePay-cash/telepay-python/issues
Project-URL: Repository, https://github.com/TelePay-cash/telepay-python
